Sum_SB2_04356/__init__.py
Sum_SB2_04356-0.0.1.dist-info/LICENCE.txt
Sum_SB2_04356-0.0.1.dist-info/METADATA
Sum_SB2_04356-0.0.1.dist-info/WHEEL
Sum_SB2_04356-0.0.1.dist-info/top_level.txt
Sum_SB2_04356-0.0.1.dist-info/RECORD
