Metadata-Version: 2.1
Name: Sum-SB2-04356
Version: 0.0.1
Summary: adding unlimited number
Home-page: UNKNOWN
Author: S.M.Hassan
Author-email: hasper786@gmail.com
License: UNKNOWN
Platform: UNKNOWN
Classifier: Programming Language :: Python :: 3
Classifier: License :: OSI Approved :: MIT License
Classifier: Operating System :: OS Independent
